hbm_runtime/HB_HBMRuntime.pyi
hbm_runtime/HB_HBMRuntime.so
hbm_runtime/__init__.py
hbm_runtime/py.typed
hbm_runtime-0.1.0.post1.dist-info/METADATA
hbm_runtime-0.1.0.post1.dist-info/WHEEL
hbm_runtime-0.1.0.post1.dist-info/RECORD
