Metadata-Version: 2.2
Name: hbm-runtime
Version: 0.1.0.post1
Summary: Python wrapper for D-Robotics libucp/libdnn libraries
Author: xiangshun.zhao et al.
Maintainer-Email: D-Robotics Developer Team <developer@d-robotics.cc>
License: Proprietary
Classifier: Programming Language :: Python :: 3
Classifier: Programming Language :: Python :: 3.10
Classifier: Programming Language :: C++
Classifier: Operating System :: POSIX :: Linux
Classifier: License :: Other/Proprietary License
Classifier: Topic :: Software Development :: Libraries
Classifier: Topic :: Software Development :: Embedded Systems
Requires-Python: >=3.10
